{
  "petitions": [
    {
      "caseInfo": "Petition: C22230028",
      "city": "Mountain View",
      "issueTypeNumber": "1",
      "argumentsAndDecisions": [
        {
          "complaintSummary": "Landlord failed to properly refund rent overcharges and security deposit, continued charging above base rent",
          "violatedCode": "CSFRA Sections 1706(a)(b) and 1707(f)",
          "reimbursement": "$6,072.11 plus additional penalties ($177.11 for delayed refund, $50.31 for utility overcharges, $8.33 for security deposit delay)",
          "complaintTiming": "February 2022 through April 2023",
          "respondentHadNotice": "Yes, through original petition and compliance notices",
          "evidenceAssessment": "Documentation showed continued overcharging above base rent and delayed refunds",
          "impactAssessment": "Tenants were overcharged for 9 months and deprived of rightful refunds"
        }
      ],
      "reimbursementJustified": "yes",
      "rentAdjustment": "Yes (5%)",
      "respondent": "Americana I, LLC",
      "hearingOfficer": "Barbara M. Anscher",
      "hearingDate": "2024-01-29",
      "filedOnDate": "2023-11-28",
      "decisionDate": "2024-03-04"
    }
  ]
}